NBTExplorer/__init__.py
nbtedit-1.0.dist-info/licenses/LICENSE
nbtedit-1.0.dist-info/METADATA
nbtedit-1.0.dist-info/WHEEL
nbtedit-1.0.dist-info/top_level.txt
nbtedit-1.0.dist-info/RECORD
