Metadata-Version: 2.4
Name: NBTEdit
Version: 1.0
Summary: NBT文件编辑器
Author-email: chenxi <chenxi20141212@126.com>
License:                     GNU GENERAL PUBLIC LICENSE
Requires-Python: >=3.8
License-File: LICENSE
Dynamic: license-file
